[{"model": "tenants.brand", "pk": 1, "fields": {"code": "SKF", "name": "SkillsFlow Academy", "legal_name": "SkillsFlow Academy (Pty) Ltd", "logo": "", "favicon": "", "primary_color": "#007bff", "secondary_color": "#6c757d", "accreditation_number": "", "seta_registration": "", "email": "", "phone": "", "website": "", "is_active": true}}, {"model": "tenants.brand", "pk": 2, "fields": {"code": "SKF-CORP", "name": "SkillsFlow Corporate", "legal_name": "SkillsFlow Corporate (Pty) Ltd", "logo": "", "favicon": "", "primary_color": "#007bff", "secondary_color": "#6c757d", "accreditation_number": "", "seta_registration": "", "email": "", "phone": "", "website": "", "is_active": true}}, {"model": "tenants.brand", "pk": 3, "fields": {"code": "SKF-ONLINE", "name": "SkillsFlow Online", "legal_name": "SkillsFlow Online (Pty) Ltd", "logo": "", "favicon": "", "primary_color": "#007bff", "secondary_color": "#6c757d", "accreditation_number": "", "seta_registration": "", "email": "", "phone": "", "website": "", "is_active": true}}, {"model": "tenants.brand", "pk": 4, "fields": {"code": "SF", "name": "SkillsFlow Academy", "legal_name": "SkillsFlow Training (Pty) Ltd", "logo": "", "favicon": "", "primary_color": "#2563eb", "secondary_color": "#64748b", "accreditation_number": "ACC-2024-001", "seta_registration": "", "email": "info@skillsflow.co.za", "phone": "+27 11 123 4567", "website": "https://skillsflow.co.za", "is_active": true}}, {"model": "tenants.brand", "pk": 5, "fields": {"code": "SKILLS", "name": "SkillsFlow Training Institute", "legal_name": "SkillsFlow Training (Pty) Ltd", "logo": "", "favicon": "", "primary_color": "#1a56db", "secondary_color": "#7e3af2", "accreditation_number": "ACC-2024-001", "seta_registration": "SETA-REG-2024-001", "email": "info@skillsflow.co.za", "phone": "+27 11 123 4567", "website": "https://skillsflow.co.za", "is_active": true}}, {"model": "tenants.brand", "pk": 6, "fields": {"code": "SKILLSFLOW", "name": "SkillsFlow Training", "legal_name": "", "logo": "", "favicon": "", "primary_color": "#007bff", "secondary_color": "#6c757d", "accreditation_number": "", "seta_registration": "", "email": "", "phone": "", "website": "", "is_active": true}}]